setup.py
putils/__init__.py
putils/dynamics.py
putils/filesystem.py
putils/patterns.py
putils/types.py
putils.egg-info/PKG-INFO
putils.egg-info/SOURCES.txt
putils.egg-info/dependency_links.txt
putils.egg-info/top_level.txt