Metadata-Version: 1.1
Name: putils
Version: 0.1.5
Summary: Python utils
Home-page: https://github.com/stanislavfeldman/putils
Author: Stanislav Feldman
Author-email: UNKNOWN
License: UNKNOWN
Keywords: utils singleton dict ternary filesystem
Platform: UNKNOWN
Classifier: Development Status :: 5 - Production/Stable
Classifier: Topic :: Software Development
